{
  "version": 8,
  "name": "Positron",
  "metadata": {
    "mapbox:autocomposite": false,
    "mapbox:type": "template",
    "mapbox:groups": {
      "b6371a3f2f5a9932464fa3867530a2e5": {
        "name": "Transportation",
        "collapsed": false
      },
      "a14c9607bc7954ba1df7205bf660433f": {
        "name": "Boundaries"
      },
      "101da9f13b64a08fa4b6ac1168e89e5f": {
        "name": "Places",
        "collapsed": false
      }
    }
  },
  "center": [
    8.501717384240095,
    47.265345646152184
  ],
  "zoom": 7.896476801499933,
  "bearing": 0,
  "pitch": 0,
  "sources": {
    "openmaptiles": {
      "url": "mapbox://morgenkaffee.8to5aq6q",
      "type": "vector"
    }
  },
  "sprite": "mapbox://sprites/morgenkaffee/ciuxun7se019v2jl8qb2jt3tf",
  "glyphs": "mapbox://fonts/morgenkaffee/{fontstack}/{range}.pbf",
  "layers": [
    {
      "id": "background",
      "type": "background",
      "interactive": true,
      "paint": {
        "background-color": "rgb(242,243,240)"
      }
    },
    {
      "id": "water",
      "type": "fill",
      "source": "openmaptiles",
      "source-layer": "water",
      "interactive": true,
      "filter": [
        "==",
        "$type",
        "Polygon"
      ],
      "layout": {
        "visibility": "visible"
      },
      "paint": {
        "fill-color": "rgb(194, 200, 202)",
        "fill-antialias": true,
        "fill-outline-color": {
          "base": 1,
          "stops": [
            [
              0,
              "hsla(180, 6%, 63%, 0.82)"
            ],
            [
              22,
              "hsla(180, 6%, 63%, 0.18)"
            ]
          ]
        }
      }
    },
    {
      "id": "landcover-ice-shelf",
      "type": "fill",
      "source": "openmaptiles",
      "source-layer": "landcover",
      "maxzoom": 8,
      "interactive": true,
      "filter": [
        "all",
        [
          "==",
          "$type",
          "Polygon"
        ],
        [
          "==",
          "subclass",
          "ice_shelf"
        ]
      ],
      "layout": {
        "visibility": "visible"
      },
      "paint": {
        "fill-color": "hsl(0, 0%, 98%)",
        "fill-opacity": 0.7
      }
    },
    {
      "id": "landcover-glacier",
      "type": "fill",
      "source": "openmaptiles",
      "source-layer": "landcover",
      "maxzoom": 8,
      "interactive": true,
      "filter": [
        "all",
        [
          "==",
          "$type",
          "Polygon"
        ],
        [
          "==",
          "subclass",
          "glacier"
        ]
      ],
      "layout": {
        "visibility": "visible"
      },
      "paint": {
        "fill-color": "hsl(0, 0%, 98%)",
        "fill-opacity": {
          "base": 1,
          "stops": [
            [
              0,
              1
            ],
            [
              8,
              0.5
            ]
          ]
        }
      }
    },
    {
      "id": "landuse-residential",
      "type": "fill",
      "source": "openmaptiles",
      "source-layer": "landuse",
      "maxzoom": 16,
      "interactive": true,
      "filter": [
        "all",
        [
          "==",
          "$type",
          "Polygon"
        ],
        [
          "==",
          "subclass",
          "residential"
        ]
      ],
      "layout": {
        "visibility": "visible"
      },
      "paint": {
        "fill-color": "rgb(234, 234, 230)",
        "fill-opacity": {
          "base": 0.6,
          "stops": [
            [
              8,
              0.8
            ],
            [
              9,
              0.6
            ]
          ]
        }
      }
    },
    {
      "id": "landcover-wood",
      "type": "fill",
      "source": "openmaptiles",
      "source-layer": "landcover",
      "minzoom": 10,
      "interactive": true,
      "filter": [
        "all",
        [
          "==",
          "$type",
          "Polygon"
        ],
        [
          "==",
          "class",
          "wood"
        ]
      ],
      "layout": {
        "visibility": "visible"
      },
      "paint": {
        "fill-color": "rgb(220,224,220)",
        "fill-opacity": {
          "base": 1,
          "stops": [
            [
              8,
              0
            ],
            [
              12,
              1
            ]
          ]
        }
      }
    },
    {
      "id": "landuse-park",
      "type": "fill",
      "source": "openmaptiles",
      "source-layer": "park",
      "interactive": true,
      "filter": [
        "all",
        [
          "==",
          "$type",
          "Polygon"
        ],
        [
          "==",
          "class",
          "national_park"
        ]
      ],
      "layout": {
        "visibility": "visible"
      },
      "paint": {
        "fill-color": "rgb(230, 233, 229)"
      }
    },
    {
      "id": "waterway",
      "type": "line",
      "source": "openmaptiles",
      "source-layer": "waterway",
      "interactive": true,
      "filter": [
        "==",
        "$type",
        "LineString"
      ],
      "layout": {
        "visibility": "visible"
      },
      "paint": {
        "line-color": "hsl(195, 17%, 78%)"
      }
    },
    {
      "id": "water-name",
      "type": "symbol",
      "source": "openmaptiles",
      "source-layer": "water_name",
      "interactive": true,
      "filter": [
        "==",
        "$type",
        "LineString"
      ],
      "layout": {
        "text-field": "{name}",
        "symbol-placement": "line",
        "text-rotation-alignment": "map",
        "symbol-spacing": 500,
        "text-font": [
          "Azo Sans Medium Italic",
          "Arial Unicode MS Regular"
        ],
        "text-size": 12
      },
      "paint": {
        "text-color": "rgb(157,169,177)",
        "text-halo-color": "rgb(242,243,240)",
        "text-halo-width": 1,
        "text-halo-blur": 1
      }
    },
    {
      "id": "building",
      "type": "fill",
      "source": "openmaptiles",
      "source-layer": "building",
      "minzoom": 12,
      "interactive": true,
      "filter": [
        "==",
        "$type",
        "Polygon"
      ],
      "paint": {
        "fill-color": "rgb(234, 234, 229)",
        "fill-outline-color": "rgb(219, 219, 218)",
        "fill-antialias": true
      }
    },
    {
      "id": "transport-motorway-tunnel-casing ",
      "type": "line",
      "metadata": {
        "mapbox:group": "b6371a3f2f5a9932464fa3867530a2e5"
      },
      "source": "openmaptiles",
      "source-layer": "transportation",
      "minzoom": 6,
      "interactive": true,
      "filter": [
        "all",
        [
          "==",
          "$type",
          "LineString"
        ],
        [
          "all",
          [
            "==",
            "brunnel",
            "tunnel"
          ],
          [
            "==",
            "class",
            "motorway"
          ]
        ]
      ],
      "layout": {
        "line-cap": "butt",
        "line-join": "miter",
        "visibility": "visible"
      },
      "paint": {
        "line-color": "rgb(213, 213, 213)",
        "line-width": {
          "base": 1.4,
          "stops": [
            [
              5.8,
              0
            ],
            [
              6,
              3
            ],
            [
              20,
              40
            ]
          ]
        },
        "line-opacity": 1
      }
    },
    {
      "id": "transport-motorway-tunnel-inner",
      "type": "line",
      "metadata": {
        "mapbox:group": "b6371a3f2f5a9932464fa3867530a2e5"
      },
      "source": "openmaptiles",
      "source-layer": "transportation",
      "minzoom": 6,
      "interactive": true,
      "filter": [
        "all",
        [
          "==",
          "$type",
          "LineString"
        ],
        [
          "all",
          [
            "==",
            "brunnel",
            "tunnel"
          ],
          [
            "==",
            "class",
            "motorway"
          ]
        ]
      ],
      "layout": {
        "line-cap": "round",
        "line-join": "round",
        "visibility": "visible"
      },
      "paint": {
        "line-color": "rgb(234,234,234)",
        "line-width": {
          "base": 1.4,
          "stops": [
            [
              4,
              2
            ],
            [
              6,
              1.3
            ],
            [
              20,
              30
            ]
          ]
        }
      }
    },
    {
      "id": "transport-path",
      "type": "line",
      "metadata": {
        "mapbox:group": "b6371a3f2f5a9932464fa3867530a2e5"
      },
      "source": "openmaptiles",
      "source-layer": "transportation",
      "interactive": true,
      "filter": [
        "all",
        [
          "==",
          "$type",
          "LineString"
        ],
        [
          "==",
          "class",
          "path"
        ]
      ],
      "layout": {
        "line-cap": "round",
        "line-join": "round",
        "visibility": "visible"
      },
      "paint": {
        "line-color": "rgb(234, 234, 234)",
        "line-width": {
          "base": 1.2,
          "stops": [
            [
              13,
              1
            ],
            [
              20,
              10
            ]
          ]
        },
        "line-opacity": 0.9
      }
    },
    {
      "id": "transport-minor",
      "type": "line",
      "metadata": {
        "mapbox:group": "b6371a3f2f5a9932464fa3867530a2e5"
      },
      "source": "openmaptiles",
      "source-layer": "transportation",
      "minzoom": 8,
      "interactive": true,
      "filter": [
        "all",
        [
          "==",
          "$type",
          "LineString"
        ],
        [
          "in",
          "class",
          "minor",
          "service",
          "track"
        ]
      ],
      "layout": {
        "line-cap": "round",
        "line-join": "round",
        "visibility": "visible"
      },
      "paint": {
        "line-color": "hsl(0, 0%, 88%)",
        "line-width": {
          "base": 1.55,
          "stops": [
            [
              13,
              1.8
            ],
            [
              20,
              20
            ]
          ]
        },
        "line-opacity": 0.9
      }
    },
    {
      "id": "transport-major-casing",
      "type": "line",
      "metadata": {
        "mapbox:group": "b6371a3f2f5a9932464fa3867530a2e5"
      },
      "source": "openmaptiles",
      "source-layer": "transportation",
      "minzoom": 11,
      "interactive": true,
      "filter": [
        "all",
        [
          "==",
          "$type",
          "LineString"
        ],
        [
          "in",
          "class",
          "primary",
          "secondary",
          "tertiary",
          "trunk"
        ]
      ],
      "layout": {
        "line-cap": "butt",
        "line-join": "miter",
        "visibility": "visible"
      },
      "paint": {
        "line-color": "rgb(213, 213, 213)",
        "line-dasharray": [
          12,
          0
        ],
        "line-width": {
          "base": 1.3,
          "stops": [
            [
              10,
              3
            ],
            [
              20,
              23
            ]
          ]
        }
      }
    },
    {
      "id": "transport-major-inner",
      "type": "line",
      "metadata": {
        "mapbox:group": "b6371a3f2f5a9932464fa3867530a2e5"
      },
      "source": "openmaptiles",
      "source-layer": "transportation",
      "minzoom": 11,
      "interactive": true,
      "filter": [
        "all",
        [
          "==",
          "$type",
          "LineString"
        ],
        [
          "in",
          "class",
          "primary",
          "secondary",
          "tertiary",
          "trunk"
        ]
      ],
      "layout": {
        "line-cap": "round",
        "line-join": "round",
        "visibility": "visible"
      },
      "paint": {
        "line-color": "#fff",
        "line-width": {
          "base": 1.3,
          "stops": [
            [
              10,
              2
            ],
            [
              20,
              20
            ]
          ]
        }
      }
    },
    {
      "id": "transport-major-subtle",
      "type": "line",
      "metadata": {
        "mapbox:group": "b6371a3f2f5a9932464fa3867530a2e5"
      },
      "source": "openmaptiles",
      "source-layer": "transportation",
      "maxzoom": 11,
      "interactive": true,
      "filter": [
        "all",
        [
          "==",
          "$type",
          "LineString"
        ],
        [
          "in",
          "class",
          "primary",
          "secondary",
          "tertiary",
          "trunk"
        ]
      ],
      "layout": {
        "line-cap": "round",
        "line-join": "round",
        "visibility": "visible"
      },
      "paint": {
        "line-color": "hsla(0, 0%, 85%, 0.69)",
        "line-width": 2
      }
    },
    {
      "id": "transport-motorway-casing",
      "type": "line",
      "metadata": {
        "mapbox:group": "b6371a3f2f5a9932464fa3867530a2e5"
      },
      "source": "openmaptiles",
      "source-layer": "transportation",
      "minzoom": 6,
      "interactive": true,
      "filter": [
        "all",
        [
          "==",
          "$type",
          "LineString"
        ],
        [
          "all",
          [
            "!in",
            "brunnel",
            "bridge",
            "tunnel"
          ],
          [
            "==",
            "class",
            "motorway"
          ]
        ]
      ],
      "layout": {
        "line-cap": "butt",
        "line-join": "miter",
        "visibility": "visible"
      },
      "paint": {
        "line-color": "rgb(213, 213, 213)",
        "line-width": {
          "base": 1.4,
          "stops": [
            [
              5.8,
              0
            ],
            [
              6,
              3
            ],
            [
              20,
              40
            ]
          ]
        },
        "line-dasharray": [
          2,
          0
        ],
        "line-opacity": 1
      }
    },
    {
      "id": "transport-motorway-inner",
      "type": "line",
      "metadata": {
        "mapbox:group": "b6371a3f2f5a9932464fa3867530a2e5"
      },
      "source": "openmaptiles",
      "source-layer": "transportation",
      "minzoom": 6,
      "interactive": true,
      "filter": [
        "all",
        [
          "==",
          "$type",
          "LineString"
        ],
        [
          "all",
          [
            "!in",
            "brunnel",
            "bridge",
            "tunnel"
          ],
          [
            "==",
            "class",
            "motorway"
          ]
        ]
      ],
      "layout": {
        "line-cap": "round",
        "line-join": "round",
        "visibility": "visible"
      },
      "paint": {
        "line-color": {
          "base": 1,
          "stops": [
            [
              5.8,
              "hsla(0, 0%, 85%, 0.53)"
            ],
            [
              6,
              "#fff"
            ]
          ]
        },
        "line-width": {
          "base": 1.4,
          "stops": [
            [
              4,
              2
            ],
            [
              6,
              1.3
            ],
            [
              20,
              30
            ]
          ]
        }
      }
    },
    {
      "id": "transport-motorway-subtle",
      "type": "line",
      "metadata": {
        "mapbox:group": "b6371a3f2f5a9932464fa3867530a2e5"
      },
      "source": "openmaptiles",
      "source-layer": "transportation",
      "maxzoom": 6,
      "interactive": true,
      "filter": [
        "all",
        [
          "==",
          "$type",
          "LineString"
        ],
        [
          "==",
          "class",
          "motorway"
        ]
      ],
      "layout": {
        "line-cap": "round",
        "line-join": "round",
        "visibility": "visible"
      },
      "paint": {
        "line-color": "hsla(0, 0%, 85%, 0.53)",
        "line-width": {
          "base": 1.4,
          "stops": [
            [
              4,
              2
            ],
            [
              6,
              1.3
            ]
          ]
        }
      }
    },
    {
      "id": "railway-service",
      "type": "line",
      "metadata": {
        "mapbox:group": "b6371a3f2f5a9932464fa3867530a2e5"
      },
      "source": "openmaptiles",
      "source-layer": "transportation",
      "minzoom": 16,
      "interactive": true,
      "filter": [
        "all",
        [
          "==",
          "$type",
          "LineString"
        ],
        [
          "all",
          [
            "==",
            "class",
            "rail"
          ],
          [
            "has",
            "service"
          ]
        ]
      ],
      "layout": {
        "visibility": "visible",
        "line-join": "round"
      },
      "paint": {
        "line-color": "#dddddd",
        "line-width": 3
      }
    },
    {
      "id": "railway-service-dashline",
      "type": "line",
      "metadata": {
        "mapbox:group": "b6371a3f2f5a9932464fa3867530a2e5"
      },
      "source": "openmaptiles",
      "source-layer": "transportation_name",
      "minzoom": 16,
      "interactive": true,
      "filter": [
        "all",
        [
          "==",
          "$type",
          "LineString"
        ],
        [
          "==",
          "class",
          "minor"
        ]
      ],
      "layout": {
        "visibility": "visible",
        "line-join": "round"
      },
      "paint": {
        "line-color": "#fafafa",
        "line-width": 2,
        "line-dasharray": [
          3,
          3
        ]
      }
    },
    {
      "id": "railway",
      "type": "line",
      "metadata": {
        "mapbox:group": "b6371a3f2f5a9932464fa3867530a2e5"
      },
      "source": "openmaptiles",
      "source-layer": "transportation",
      "minzoom": 13,
      "interactive": true,
      "filter": [
        "all",
        [
          "==",
          "$type",
          "LineString"
        ],
        [
          "all",
          [
            "!has",
            "service"
          ],
          [
            "==",
            "class",
            "rail"
          ]
        ]
      ],
      "layout": {
        "visibility": "visible",
        "line-join": "round"
      },
      "paint": {
        "line-color": "#dddddd",
        "line-width": {
          "base": 1.3,
          "stops": [
            [
              16,
              3
            ],
            [
              20,
              7
            ]
          ]
        }
      }
    },
    {
      "id": "railway-dashline",
      "metadata": {
        "mapbox:group": "b6371a3f2f5a9932464fa3867530a2e5"
      },
      "ref": "railway",
      "interactive": true,
      "paint": {
        "line-color": "#fafafa",
        "line-width": {
          "base": 1.3,
          "stops": [
            [
              16,
              2
            ],
            [
              20,
              6
            ]
          ]
        },
        "line-dasharray": [
          3,
          3
        ]
      }
    },
    {
      "id": "transport-name-other",
      "type": "symbol",
      "metadata": {
        "mapbox:group": "b6371a3f2f5a9932464fa3867530a2e5"
      },
      "source": "openmaptiles",
      "source-layer": "transportation_name",
      "interactive": true,
      "filter": [
        "all",
        [
          "!=",
          "class",
          "motorway"
        ],
        [
          "==",
          "$type",
          "LineString"
        ]
      ],
      "layout": {
        "text-size": 10,
        "text-max-angle": 30,
        "text-transform": "uppercase",
        "symbol-spacing": 350,
        "text-font": [
          "Azo Sans Regular",
          "Arial Unicode MS Regular"
        ],
        "symbol-placement": "line",
        "visibility": "visible",
        "text-rotation-alignment": "map",
        "text-pitch-alignment": "viewport",
        "text-field": "{name}"
      },
      "paint": {
        "text-color": "#bbb",
        "text-halo-color": "#fff",
        "text-translate": [
          0,
          0
        ],
        "text-halo-width": 2,
        "text-halo-blur": 1
      }
    },
    {
      "id": "transport-name-motorway",
      "type": "symbol",
      "metadata": {
        "mapbox:group": "b6371a3f2f5a9932464fa3867530a2e5"
      },
      "source": "openmaptiles",
      "source-layer": "transportation_name",
      "interactive": true,
      "filter": [
        "all",
        [
          "==",
          "$type",
          "LineString"
        ],
        [
          "==",
          "class",
          "motorway"
        ]
      ],
      "layout": {
        "text-size": 10,
        "symbol-spacing": 350,
        "text-font": [
          "Azo Sans Light",
          "Arial Unicode MS Regular"
        ],
        "symbol-placement": "line",
        "visibility": "visible",
        "text-rotation-alignment": "viewport",
        "text-pitch-alignment": "viewport",
        "text-field": "{ref}"
      },
      "paint": {
        "text-color": "rgb(117, 129, 145)",
        "text-halo-color": "hsl(0, 0%, 100%)",
        "text-translate": [
          0,
          2
        ],
        "text-halo-width": 1,
        "text-halo-blur": 1
      }
    },
    {
      "id": "boundary-state",
      "type": "line",
      "metadata": {
        "mapbox:group": "b6371a3f2f5a9932464fa3867530a2e5"
      },
      "source": "openmaptiles",
      "source-layer": "boundary",
      "interactive": true,
      "filter": [
        "==",
        "admin_level",
        4
      ],
      "layout": {
        "line-cap": "round",
        "line-join": "round",
        "visibility": "visible"
      },
      "paint": {
        "line-color": "rgb(230, 204, 207)",
        "line-width": {
          "base": 1.3,
          "stops": [
            [
              3,
              1
            ],
            [
              22,
              15
            ]
          ]
        },
        "line-blur": 0.4,
        "line-dasharray": [
          2,
          2
        ],
        "line-opacity": 1
      }
    },
    {
      "id": "boundary-country",
      "type": "line",
      "metadata": {
        "mapbox:group": "a14c9607bc7954ba1df7205bf660433f"
      },
      "source": "openmaptiles",
      "source-layer": "boundary",
      "interactive": true,
      "filter": [
        "==",
        "admin_level",
        2
      ],
      "layout": {
        "line-cap": "round",
        "line-join": "round"
      },
      "paint": {
        "line-color": "rgb(230, 204, 207)",
        "line-width": {
          "base": 1.1,
          "stops": [
            [
              3,
              1
            ],
            [
              22,
              20
            ]
          ]
        },
        "line-blur": {
          "base": 1,
          "stops": [
            [
              0,
              0.4
            ],
            [
              22,
              4
            ]
          ]
        },
        "line-opacity": 1
      }
    },
    {
      "id": "place-other",
      "type": "symbol",
      "metadata": {
        "mapbox:group": "101da9f13b64a08fa4b6ac1168e89e5f"
      },
      "source": "openmaptiles",
      "source-layer": "place",
      "maxzoom": 14,
      "interactive": true,
      "filter": [
        "all",
        [
          "==",
          "$type",
          "Point"
        ],
        [
          "all",
          [
            "!in",
            "subclass",
            "city",
            "suburb",
            "town",
            "village"
          ],
          [
            "in",
            "class",
            "settlement",
            "subregion"
          ]
        ]
      ],
      "layout": {
        "text-size": 10,
        "text-transform": "uppercase",
        "text-font": [
          "Azo Sans Regular",
          "Arial Unicode MS Regular"
        ],
        "text-justify": "center",
        "visibility": "visible",
        "text-offset": [
          0.5,
          0
        ],
        "text-anchor": "center",
        "text-field": "{name_en}"
      },
      "paint": {
        "text-color": "rgb(117, 129, 145)",
        "text-halo-color": "rgb(242,243,240)",
        "text-halo-width": 1,
        "text-halo-blur": 1
      }
    },
    {
      "id": "place-suburb",
      "type": "symbol",
      "metadata": {
        "mapbox:group": "101da9f13b64a08fa4b6ac1168e89e5f"
      },
      "source": "openmaptiles",
      "source-layer": "place",
      "maxzoom": 15,
      "interactive": true,
      "filter": [
        "all",
        [
          "==",
          "$type",
          "Point"
        ],
        [
          "==",
          "subclass",
          "suburb"
        ]
      ],
      "layout": {
        "text-size": 10,
        "text-transform": "uppercase",
        "text-font": [
          "Azo Sans Regular",
          "Arial Unicode MS Regular"
        ],
        "text-justify": "center",
        "visibility": "visible",
        "text-offset": [
          0.5,
          0
        ],
        "text-anchor": "center",
        "text-field": "{name_en}"
      },
      "paint": {
        "text-color": "rgb(117, 129, 145)",
        "text-halo-color": "rgb(242,243,240)",
        "text-halo-width": 1,
        "text-halo-blur": 1
      }
    },
    {
      "id": "place-village",
      "type": "symbol",
      "metadata": {
        "mapbox:group": "101da9f13b64a08fa4b6ac1168e89e5f"
      },
      "source": "openmaptiles",
      "source-layer": "place",
      "maxzoom": 14,
      "interactive": true,
      "filter": [
        "all",
        [
          "==",
          "$type",
          "Point"
        ],
        [
          "==",
          "subclass",
          "village"
        ]
      ],
      "layout": {
        "text-size": 10,
        "text-transform": "uppercase",
        "text-font": [
          "Azo Sans Regular",
          "Arial Unicode MS Regular"
        ],
        "text-justify": "left",
        "visibility": "visible",
        "text-offset": [
          0.5,
          0.2
        ],
        "icon-size": 0.4,
        "text-anchor": "left",
        "text-field": "{name_en}"
      },
      "paint": {
        "text-color": "rgb(117, 129, 145)",
        "text-halo-color": "rgb(242,243,240)",
        "text-halo-width": 1,
        "text-halo-blur": 1,
        "icon-opacity": 0.7
      }
    },
    {
      "id": "place-town",
      "type": "symbol",
      "metadata": {
        "mapbox:group": "101da9f13b64a08fa4b6ac1168e89e5f"
      },
      "source": "openmaptiles",
      "source-layer": "place",
      "maxzoom": 15,
      "interactive": true,
      "filter": [
        "all",
        [
          "==",
          "$type",
          "Point"
        ],
        [
          "==",
          "subclass",
          "town"
        ]
      ],
      "layout": {
        "text-size": 10,
        "icon-image": {
          "base": 1,
          "stops": [
            [
              0,
              "circle-11"
            ],
            [
              9,
              ""
            ]
          ]
        },
        "text-transform": "uppercase",
        "text-font": [
          "Azo Sans Regular",
          "Arial Unicode MS Regular"
        ],
        "text-justify": "left",
        "visibility": "visible",
        "text-offset": [
          0.5,
          0.2
        ],
        "icon-size": 0.4,
        "text-anchor": {
          "base": 1,
          "stops": [
            [
              0,
              "left"
            ],
            [
              8,
              "center"
            ]
          ]
        },
        "text-field": "{name_en}"
      },
      "paint": {
        "text-color": "rgb(117, 129, 145)",
        "text-halo-color": "rgb(242,243,240)",
        "text-halo-width": 1,
        "text-halo-blur": 1,
        "icon-opacity": 0.7
      }
    },
    {
      "id": "place-city",
      "type": "symbol",
      "metadata": {
        "mapbox:group": "101da9f13b64a08fa4b6ac1168e89e5f"
      },
      "source": "openmaptiles",
      "source-layer": "place",
      "maxzoom": 14,
      "interactive": true,
      "filter": [
        "all",
        [
          "==",
          "$type",
          "Point"
        ],
        [
          "all",
          [
            "!=",
            "capital",
            2
          ],
          [
            "==",
            "subclass",
            "city"
          ],
          [
            ">",
            "rank",
            3
          ]
        ]
      ],
      "layout": {
        "text-size": 10,
        "icon-image": {
          "base": 1,
          "stops": [
            [
              0,
              "circle-11"
            ],
            [
              9,
              ""
            ]
          ]
        },
        "text-transform": "uppercase",
        "text-font": [
          "Azo Sans Regular",
          "Arial Unicode MS Regular"
        ],
        "text-justify": "left",
        "visibility": "visible",
        "text-offset": [
          0.5,
          0.2
        ],
        "icon-size": 0.4,
        "text-anchor": {
          "base": 1,
          "stops": [
            [
              0,
              "left"
            ],
            [
              8,
              "center"
            ]
          ]
        },
        "text-field": "{name_en}"
      },
      "paint": {
        "text-color": "rgb(117, 129, 145)",
        "text-halo-color": "rgb(242,243,240)",
        "text-halo-width": 1,
        "text-halo-blur": 1,
        "icon-opacity": 0.7
      }
    },
    {
      "id": "place-capital",
      "type": "symbol",
      "metadata": {
        "mapbox:group": "101da9f13b64a08fa4b6ac1168e89e5f"
      },
      "source": "openmaptiles",
      "source-layer": "place",
      "maxzoom": 12,
      "interactive": true,
      "filter": [
        "all",
        [
          "==",
          "$type",
          "Point"
        ],
        [
          "all",
          [
            "==",
            "capital",
            2
          ],
          [
            "==",
            "subclass",
            "city"
          ]
        ]
      ],
      "layout": {
        "text-size": 14,
        "icon-image": {
          "base": 1,
          "stops": [
            [
              0,
              "star-11"
            ],
            [
              9,
              ""
            ]
          ]
        },
        "text-transform": "uppercase",
        "text-font": [
          "Azo Sans Regular",
          "Arial Unicode MS Regular"
        ],
        "text-justify": "left",
        "visibility": "visible",
        "text-offset": [
          0.5,
          0.2
        ],
        "icon-size": 1,
        "text-anchor": {
          "base": 1,
          "stops": [
            [
              0,
              "left"
            ],
            [
              8,
              "center"
            ]
          ]
        },
        "text-field": "{name}"
      },
      "paint": {
        "text-color": "rgb(117, 129, 145)",
        "text-halo-color": "rgb(242,243,240)",
        "text-halo-width": 1,
        "text-halo-blur": 1,
        "icon-opacity": 0.7
      }
    },
    {
      "id": "place-city-large",
      "type": "symbol",
      "metadata": {
        "mapbox:group": "101da9f13b64a08fa4b6ac1168e89e5f"
      },
      "source": "openmaptiles",
      "source-layer": "place",
      "maxzoom": 12,
      "interactive": true,
      "filter": [
        "all",
        [
          "==",
          "$type",
          "Point"
        ],
        [
          "all",
          [
            "!=",
            "capital",
            2
          ],
          [
            "<=",
            "rank",
            3
          ],
          [
            "==",
            "subclass",
            "city"
          ]
        ]
      ],
      "layout": {
        "text-size": 14,
        "icon-image": {
          "base": 1,
          "stops": [
            [
              0,
              "circle-11"
            ],
            [
              9,
              ""
            ]
          ]
        },
        "text-transform": "uppercase",
        "text-font": [
          "Azo Sans Regular",
          "Arial Unicode MS Regular"
        ],
        "text-justify": "left",
        "visibility": "visible",
        "text-offset": [
          0.5,
          0.2
        ],
        "icon-size": 0.4,
        "text-anchor": {
          "base": 1,
          "stops": [
            [
              0,
              "left"
            ],
            [
              8,
              "center"
            ]
          ]
        },
        "text-field": "{name}"
      },
      "paint": {
        "text-color": "rgb(117, 129, 145)",
        "text-halo-color": "rgb(242,243,240)",
        "text-halo-width": 1,
        "text-halo-blur": 1,
        "icon-opacity": 0.7
      }
    },
    {
      "id": "place-state",
      "type": "symbol",
      "metadata": {
        "mapbox:group": "101da9f13b64a08fa4b6ac1168e89e5f"
      },
      "source": "openmaptiles",
      "source-layer": "place",
      "maxzoom": 12,
      "interactive": true,
      "filter": [
        "all",
        [
          "==",
          "$type",
          "Point"
        ],
        [
          "==",
          "class",
          "state"
        ]
      ],
      "layout": {
        "visibility": "visible",
        "text-field": "{name_en}",
        "text-font": [
          "Azo Sans Regular",
          "Arial Unicode MS Regular"
        ],
        "text-transform": "uppercase",
        "text-size": 10
      },
      "paint": {
        "text-color": "rgb(113, 129, 144)",
        "text-halo-color": "rgb(242,243,240)",
        "text-halo-width": 1,
        "text-halo-blur": 1
      }
    },
    {
      "id": "place-country-other",
      "type": "symbol",
      "metadata": {
        "mapbox:group": "101da9f13b64a08fa4b6ac1168e89e5f"
      },
      "source": "openmaptiles",
      "source-layer": "place",
      "maxzoom": 8,
      "interactive": true,
      "filter": [
        "all",
        [
          "==",
          "$type",
          "Point"
        ],
        [
          "all",
          [
            "==",
            "class",
            "country"
          ],
          [
            ">=",
            "rank",
            2
          ]
        ]
      ],
      "layout": {
        "visibility": "visible",
        "text-field": "{name_en}",
        "text-font": [
          "Azo Sans Regular",
          "Arial Unicode MS Regular"
        ],
        "text-transform": "uppercase",
        "text-size": {
          "base": 1,
          "stops": [
            [
              0,
              10
            ],
            [
              6,
              12
            ]
          ]
        }
      },
      "paint": {
        "text-halo-width": 1.4,
        "text-halo-color": "rgba(236,236,234,0.7)",
        "text-color": {
          "base": 1,
          "stops": [
            [
              3,
              "rgb(157,169,177)"
            ],
            [
              4,
              "rgb(153, 153, 153)"
            ]
          ]
        }
      }
    },
    {
      "id": "place-country-major",
      "type": "symbol",
      "metadata": {
        "mapbox:group": "101da9f13b64a08fa4b6ac1168e89e5f"
      },
      "source": "openmaptiles",
      "source-layer": "place",
      "maxzoom": 6,
      "interactive": true,
      "filter": [
        "all",
        [
          "==",
          "$type",
          "Point"
        ],
        [
          "all",
          [
            "<=",
            "rank",
            1
          ],
          [
            "==",
            "class",
            "country"
          ]
        ]
      ],
      "layout": {
        "visibility": "visible",
        "text-field": "{name_en}",
        "text-font": [
          "Azo Sans Regular",
          "Arial Unicode MS Regular"
        ],
        "text-transform": "uppercase",
        "text-size": {
          "base": 1.4,
          "stops": [
            [
              0,
              10
            ],
            [
              3,
              12
            ],
            [
              4,
              14
            ]
          ]
        },
        "text-anchor": "center"
      },
      "paint": {
        "text-halo-width": 1.4,
        "text-halo-color": "rgba(236,236,234,0.7)",
        "text-color": {
          "base": 1,
          "stops": [
            [
              3,
              "rgb(157,169,177)"
            ],
            [
              4,
              "rgb(153, 153, 153)"
            ]
          ]
        }
      }
    }
  ]
}
